{
	"name": "Custom High Contrast Theme",
	"type": "dark",
	"colors": {
	  "editor.background": "#0D111C",
	  "editor.foreground": "#F3DDCD",
	  "editorCursor.foreground": "#F3DDCD",
	  "editor.lineHighlightBackground": "#0D111C",
	  "editor.selectionBackground": "#1D2538",
	  "editor.selectionHighlightBackground": "#1D2538",
	  "editor.findMatchBackground": "#F3DDCD",
	  "editor.findMatchHighlightBackground": "#F3DDCD",
	  "editor.hoverHighlightBackground": "#0D111C",
	  "activityBar.background": "#111424",
	  "sideBar.background": "#111424",
	  "sideBar.foreground": "#F3DDCD",
	  "sideBar.border": "#0D111C",
	  "statusBar.background": "#111424",
	  "statusBar.foreground": "#F3DDCD",
	  "titleBar.activeBackground": "#111424",
	  "titleBar.activeForeground": "#F3DDCD",
	  "titleBar.inactiveBackground": "#0D111C",
	  "titleBar.inactiveForeground": "#F3DDCD",
	  "panel.background": "#111424",
	  "panel.border": "#0D111C",
	  "terminal.background": "#0D111C",  
	  "terminal.foreground": "#F3DDCD",   
	  "menu.background": "#0D111C",
	  "menu.foreground": "#F3DDCD",
	  "menu.selectionBackground": "#1D2538",
	  "menu.selectionForeground": "#F3DDCD",
	  "editorBracketMatch.background": "#0D111C",
	  "editorBracketMatch.border": "#0D111C",
	  "editorGroupHeader.tabsBackground": "#111424",
	  "editorGroupHeader.tabsBorder": "#0D111C",
	  "editorGroup.border": "#0D111C",
	  "tab.activeBackground": "#0D111C",
	  "tab.inactiveBackground": "#111424",
	  "tab.border": "#0D111C",
	  "editorGutter.background": "#0D111C",
	  "editorGutter.modifiedBackground": "#F3DDCD",
	  "editorGutter.addedBackground": "#F3DDCD",
	  "editorGutter.deletedBackground": "#F3DDCD",
	  "editor.selectionForeground": "#111424",
	  "editorWidget.background": "#111424",
	  "editorWidget.border": "#0D111C",
	  "findWidget.background": "#111424",
	  "findWidget.border": "#0D111C",
	  "findWidget.titleBackground": "#111424",
	  "findWidget.textBackground": "#0D111C",
	  "quickInput.background": "#111424",
	  "quickInput.foreground": "#F3DDCD",
	  "quickInput.list.background": "#111424",
	  "quickInput.list.focusBackground": "#1D2538",
	  "quickInput.list.focusForeground": "#F3DDCD",
	  "peekView.background": "#111424",
	  "peekView.border": "#0D111C",
	  "peekViewEditor.background": "#0D111C",
	  "peekViewEditor.border": "#0D111C",
	  "peekViewTitle.background": "#111424",
	  "peekViewTitleDescription.foreground": "#F3DDCD",
	  "scrollbarSlider.background": "#0D111C",
	  "scrollbarSlider.hoverBackground": "#F3DDCD",
	  "scrollbarSlider.activeBackground": "#F3DDCD"
	},
	"tokenColors": [
	  {
		"scope": "comment",
		"settings": { "foreground": "#8695B7" }  // Slightly lighter comment color for better readability
	  },
	  {
		"scope": "keyword",
		"settings": { "foreground": "#FF79C6", "fontStyle": "bold" }  // Bright pink keywords for contrast
	  },
	  {
		"scope": "string",
		"settings": { "foreground": "#A1EFD3" }  // Light cyan for string literals, easy on the eyes
	  },
	  {
		"scope": "variable",
		"settings": { "foreground": "#F3DDCD" }  // Light yellow for variables
	  },
	  {
		"scope": "function",
		"settings": { "foreground": "#FFC777", "fontStyle": "bold" }  // Bright yellow for function names
	  },
	  {
		"scope": "number",
		"settings": { "foreground": "#D4BFFF" }  // Lavender for numbers, contrasting but soft
	  },
	  {
		"scope": "type",
		"settings": { "foreground": "#FFCC99" }  // Soft peach for types
	  },
	  {
		"scope": "class-name",
		"settings": { "foreground": "#FFEE99" }  // Light gold for class names, stands out clearly
	  },
	  {
		"scope": "constant",
		"settings": { "foreground": "#F28B82" }  // Soft red for constants, subtle yet readable
	  },
	  {
		"scope": "operator",
		"settings": { "foreground": "#FF79C6" }  // Pinkish color for operators, visible but not too harsh
	  },
	  {
		"scope": "punctuation",
		"settings": { "foreground": "#F3DDCD" }  // Match punctuation color to variables, enhancing cohesion
	  },
	  {
		"scope": "storage",
		"settings": { "foreground": "#FF9D72" }  // Storage keywords in orange for clarity
	  },
	  {
		"scope": "delimiter",
		"settings": { "foreground": "#0D111C" }  // Dark delimiter for less distraction
	  },
	  {
		"scope": "meta.tag",
		"settings": { "foreground": "#FF79C6" }  // Tag names in bright pink for contrast
	  },
	  {
		"scope": "meta.attribute-name",
		"settings": { "foreground": "#A1EFD3" }  // Light cyan for attribute names
	  },
	  {
		"scope": "meta.attribute-value",
		"settings": { "foreground": "#FFC777" }  // Yellow for attribute values to match the overall style
	  },
	  {
		"scope": "entity.name.function",
		"settings": { "foreground": "#FFC777" }  // Functions in bright yellow, making them pop
	  },
	  {
		"scope": "support.type",
		"settings": { "foreground": "#FFCC99" }  // Soft peach for support types
	  },
	  {
		"scope": "invalid",
		"settings": { "foreground": "#FF5555", "fontStyle": "bold, underline" }  // Red for invalid code
	  }
	]
  }
  